videosdk/__init__.py
videosdk/_events.py
videosdk/custom_audio_track.py
videosdk/custom_video_track.py
videosdk/event_handler.py
videosdk/exceptions.py
videosdk/meeting.py
videosdk/participant.py
videosdk/pubsub.py
videosdk/room_client.py
videosdk/stream.py
videosdk/utils.py
videosdk/videosdk.py
videosdk/lib/__init__.py
videosdk/lib/pymediasoup/__init__.py
videosdk/lib/pymediasoup/__version__.py
videosdk/lib/pymediasoup/consumer.py
videosdk/lib/pymediasoup/data_consumer.py
videosdk/lib/pymediasoup/data_producer.py
videosdk/lib/pymediasoup/device.py
videosdk/lib/pymediasoup/emitter.py
videosdk/lib/pymediasoup/errors.py
videosdk/lib/pymediasoup/ortc.py
videosdk/lib/pymediasoup/producer.py
videosdk/lib/pymediasoup/rtp_parameters.py
videosdk/lib/pymediasoup/scalability_modes.py
videosdk/lib/pymediasoup/sctp_parameters.py
videosdk/lib/pymediasoup/transport.py
videosdk/lib/pymediasoup/handlers/__init__.py
videosdk/lib/pymediasoup/handlers/aiortc_handler.py
videosdk/lib/pymediasoup/handlers/handler_interface.py
videosdk/lib/pymediasoup/handlers/sdp/__init__.py
videosdk/lib/pymediasoup/handlers/sdp/common_utils.py
videosdk/lib/pymediasoup/handlers/sdp/media_section.py
videosdk/lib/pymediasoup/handlers/sdp/remote_sdp.py
videosdk/lib/pymediasoup/handlers/sdp/unified_plan_utils.py
videosdk/lib/pymediasoup/models/__init__.py
videosdk/lib/pymediasoup/models/handler_interface.py
videosdk/lib/pymediasoup/models/transport.py
videosdk/worker/__init__.py
videosdk/worker/character_state.py
videosdk/worker/character_worker.py
videosdk/worker/client.py
videosdk/worker/schemas.py
videosdk/worker/worker_service.py
videosdk/worker/context/__init__.py
videosdk/worker/context/character_context.py
videosdk/worker/context/character_intent.py
videosdk/worker/context/character_memory.py
videosdk/worker/context/character_vision.py
videosdk-0.2.9.dist-info/METADATA
videosdk-0.2.9.dist-info/WHEEL
videosdk-0.2.9.dist-info/top_level.txt
videosdk-0.2.9.dist-info/RECORD
