Metadata-Version: 2.4
Name: videosdk
Version: 0.2.9
Summary: VideoSDK Python SDK
Author: videosdk
Author-email: sdk@videosdk.live
License-Expression: MIT
Project-URL: Home, https://docs.videosdk.live
Project-URL: Documentation, https://docs.videosdk.live
Project-URL: Source, https://docs.videosdk.live
Project-URL: Website, https://videosdk.live
Keywords: ml,webrtc,audio,video,ai,videosdk
Classifier: Development Status :: 4 - Beta
Classifier: Intended Audience :: Developers
Classifier: Topic :: Communications :: Conferencing
Classifier: Topic :: Multimedia :: Sound/Audio
Classifier: Topic :: Multimedia :: Video
Classifier: Topic :: Scientific/Engineering :: Artificial Intelligence
Requires-Python: >=3.11
Requires-Dist: pydantic>=1.10.15
Requires-Dist: vsaiortc>=0.0.6
Requires-Dist: h264-profile-level-id<1.1.0,>=1.0.0
Requires-Dist: sdp-transform<1.2.0,>=1.1.0
Requires-Dist: pyee>=13.0.0
Requires-Dist: av<17.0.0,>=14.0.0
Requires-Dist: websockets<=15.0.1,>=12.0.0
Requires-Dist: requests<2.32.0,>=2.3.1
Requires-Dist: pylibsrtp>=0.10.0
Requires-Dist: pyopenssl>=24.0.0
Requires-Dist: pycryptodome==3.20.0
Requires-Dist: pillow>=11.1.0
Dynamic: author-email
